gaddam_multiply/__init__.py
gaddam_multiply/multiply.py
gaddam_multiply-0.1.0.dist-info/METADATA
gaddam_multiply-0.1.0.dist-info/WHEEL
gaddam_multiply-0.1.0.dist-info/top_level.txt
gaddam_multiply-0.1.0.dist-info/RECORD
