Metadata-Version: 2.1
Name: gaddam-multiply
Version: 0.1.0
Summary: Demo library
Home-page: https://medium-multiply.readthedocs.io/
Author: Sagar Gaddam
Author-email: sagar0205@gmail.com
License: MIT
Platform: UNKNOWN
Classifier: Intended Audience :: Developers
Classifier: License :: OSI Approved :: MIT License
Classifier: Programming Language :: Python
Classifier: Programming Language :: Python :: 3
Classifier: Programming Language :: Python :: 3.6
Classifier: Programming Language :: Python :: 3.7
Classifier: Programming Language :: Python :: 3.8
Classifier: Programming Language :: Python :: 3.9
Classifier: Operating System :: OS Independent
Requires-Dist: numpy
